rbd_iscsi_client/__init__.py
rbd_iscsi_client/client.py
rbd_iscsi_client/exceptions.py
rbd_iscsi_client/i18n.py
rbd_iscsi_client/tests/__init__.py
rbd_iscsi_client/tests/test_client.py
rbd_iscsi_client/tests/test_client_request.py
rbd_iscsi_client/tests/test_exceptions.py
rbd_iscsi_client-0.1.8.dist-info/LICENSE
rbd_iscsi_client-0.1.8.dist-info/METADATA
rbd_iscsi_client-0.1.8.dist-info/WHEEL
rbd_iscsi_client-0.1.8.dist-info/pbr.json
rbd_iscsi_client-0.1.8.dist-info/top_level.txt
rbd_iscsi_client-0.1.8.dist-info/RECORD
