Metadata-Version: 2.1
Name: rbd-iscsi-client
Version: 0.1.8
Summary: "REST client to talk to rbd-target-api"
Home-page: http://github.com/hemna/rbd-iscsi-client
Author: Walter A. Boring IV
Author-email: waboring@hemna.com
License: UNKNOWN
Platform: UNKNOWN
Classifier: Environment :: OpenStack
Classifier: Intended Audience :: Information Technology
Classifier: Intended Audience :: System Administrators
Classifier: License :: OSI Approved :: Apache Software License
Classifier: Natural Language :: English
Classifier: Programming Language :: Python :: 3
Classifier: Programming Language :: Python :: 3.6
Classifier: Programming Language :: Python :: 3.7
Classifier: Programming Language :: Python :: 3.8
Requires-Dist: Babel (!=2.4.0,>=2.3.4)
Requires-Dist: oslo.i18n (>=3.24.0)
Requires-Dist: oslo.log (>=3.44.0)
Requires-Dist: oslo.utils (>=3.34.0)
Requires-Dist: pbr (!=2.1.0,>=5.4.1)
Requires-Dist: requests (!=2.20.0,>=2.14.2)
Requires-Dist: six (>=1.10.0)
